scripts/install-hooks.py
scripts/pre-commit.py
llm_code_lens/__init__.py
llm_code_lens/cli.py
llm_code_lens/menu.py
llm_code_lens/version.py
llm_code_lens/analyzer/__init__.py
llm_code_lens/analyzer/base.py
llm_code_lens/analyzer/config.py
llm_code_lens/analyzer/javascript.py
llm_code_lens/analyzer/python.py
llm_code_lens/analyzer/sql.py
llm_code_lens/formatters/__init__.py
llm_code_lens/formatters/llm.py
llm_code_lens/processors/__init__.py
llm_code_lens/processors/insights.py
llm_code_lens/processors/summary.py
llm_code_lens/utils/__init__.py
llm_code_lens/utils/gitignore.py
llm_code_lens/utils/tree.py
llm_code_lens-0.6.1.dist-info/METADATA
llm_code_lens-0.6.1.dist-info/WHEEL
llm_code_lens-0.6.1.dist-info/entry_points.txt
llm_code_lens-0.6.1.dist-info/licenses/LICENSE
llm_code_lens-0.6.1.dist-info/RECORD
