Metadata-Version: 2.4
Name: llm_code_lens
Version: 0.6.1
Summary: Ultra-fast intelligent code analysis tool for LLM context generation with Tree-sitter
Project-URL: Homepage, https://github.com/SikamikanikoBG/codelens.git
Project-URL: Bug Tracker, https://github.com/SikamikanikoBG/codelens/issues
Project-URL: Documentation, https://github.com/SikamikanikoBG/codelens/blob/main/README.md
Project-URL: Source Code, https://github.com/SikamikanikoBG/codelens
Author-email: Arsen Apostolov <arsen.apostolov@gmail.com>
License-Expression: MIT
License-File: LICENSE
Keywords: code analysis,llm,performance,sql analysis,static analysis,tree-sitter
Classifier: Development Status :: 4 - Beta
Classifier: Intended Audience :: Developers
Classifier: License :: OSI Approved :: MIT License
Classifier: Programming Language :: Python :: 3
Classifier: Programming Language :: Python :: 3.8
Classifier: Programming Language :: Python :: 3.9
Classifier: Programming Language :: Python :: 3.10
Classifier: Programming Language :: Python :: 3.11
Classifier: Programming Language :: Python :: 3.12
Classifier: Topic :: Software Development :: Code Generators
Classifier: Topic :: Software Development :: Libraries :: Python Modules
Classifier: Topic :: Text Processing :: Linguistic
Requires-Python: >=3.8
Requires-Dist: click>=8.0.0
Requires-Dist: packaging>=22.0.0
Requires-Dist: pathspec>=0.11.0
Requires-Dist: pyodbc>=4.0.39; platform_system != 'Darwin'
Requires-Dist: pyperclip>=1.8.0
Requires-Dist: requests>=2.28.0
Requires-Dist: rich>=10.0.0
Requires-Dist: tiktoken>=0.5.0
Requires-Dist: tomli>=2.0.0; python_version < '3.11'
Requires-Dist: tree-sitter-javascript>=0.20.0
Requires-Dist: tree-sitter-python>=0.20.0
Requires-Dist: tree-sitter-typescript>=0.20.0
Requires-Dist: tree-sitter>=0.20.0
Requires-Dist: windows-curses; platform_system == 'Windows'
Provides-Extra: dev
Requires-Dist: black>=23.0.0; extra == 'dev'
Requires-Dist: isort>=5.13.0; extra == 'dev'
Requires-Dist: mypy>=1.0.0; extra == 'dev'
Requires-Dist: pytest-cov>=4.0.0; extra == 'dev'
Requires-Dist: pytest-mock>=3.10.0; extra == 'dev'
Requires-Dist: pytest>=7.0.0; extra == 'dev'
Requires-Dist: radon>=5.0.0; extra == 'dev'
Provides-Extra: fast
Requires-Dist: click>=8.0.0; extra == 'fast'
Requires-Dist: packaging>=22.0.0; extra == 'fast'
Requires-Dist: pathspec>=0.11.0; extra == 'fast'
Requires-Dist: pyperclip>=1.8.0; extra == 'fast'
Requires-Dist: requests>=2.28.0; extra == 'fast'
Requires-Dist: rich>=10.0.0; extra == 'fast'
Requires-Dist: tiktoken>=0.5.0; extra == 'fast'
Requires-Dist: tomli>=2.0.0; (python_version < '3.11') and extra == 'fast'
Requires-Dist: tree-sitter-javascript>=0.20.0; extra == 'fast'
Requires-Dist: tree-sitter-python>=0.20.0; extra == 'fast'
Requires-Dist: tree-sitter-typescript>=0.20.0; extra == 'fast'
Requires-Dist: tree-sitter>=0.20.0; extra == 'fast'
Requires-Dist: windows-curses; (platform_system == 'Windows') and extra == 'fast'
Provides-Extra: full
Requires-Dist: click>=8.0.0; extra == 'full'
Requires-Dist: packaging>=22.0.0; extra == 'full'
Requires-Dist: pathspec>=0.11.0; extra == 'full'
Requires-Dist: pyodbc>=4.0.39; extra == 'full'
Requires-Dist: pyperclip>=1.8.0; extra == 'full'
Requires-Dist: requests>=2.28.0; extra == 'full'
Requires-Dist: rich>=10.0.0; extra == 'full'
Requires-Dist: tiktoken>=0.5.0; extra == 'full'
Requires-Dist: tomli>=2.0.0; (python_version < '3.11') and extra == 'full'
Requires-Dist: tree-sitter-javascript>=0.20.0; extra == 'full'
Requires-Dist: tree-sitter-python>=0.20.0; extra == 'full'
Requires-Dist: tree-sitter-typescript>=0.20.0; extra == 'full'
Requires-Dist: tree-sitter>=0.20.0; extra == 'full'
Requires-Dist: windows-curses; (platform_system == 'Windows') and extra == 'full'
